fastapi_versioned/__init__.py
fastapi_versioned/routing.py
fastapi_versioned/versioning.py
fastapi_versioned-0.2.1.dist-info/LICENSE
fastapi_versioned-0.2.1.dist-info/WHEEL
fastapi_versioned-0.2.1.dist-info/METADATA
fastapi_versioned-0.2.1.dist-info/RECORD
