Metadata-Version: 2.1
Name: fastapi-versioned
Version: 0.2.1
Summary: api versioning for fastapi web applications
License: MIT
Author: dorklein
Author-email: dorklein2@gmail.com
Requires-Python: >=3.7,<4.0
Classifier: License :: OSI Approved :: MIT License
Classifier: Programming Language :: Python :: 3
Classifier: Programming Language :: Python :: 3.7
Classifier: Programming Language :: Python :: 3.8
Classifier: Programming Language :: Python :: 3.9
Classifier: Programming Language :: Python :: 3.10
Classifier: Programming Language :: Python :: 3.11
Requires-Dist: fastapi (>=0.85.1,<0.86.0)
